odinweb/__init__.py
odinweb/django/__init__.py
odinweb/django/models.py
odinweb/django/api/__init__.py
odinweb/django/api/middleware.py
odinweb/django/api/models.py
odinweb.django-0.4.3.dist-info/METADATA
odinweb.django-0.4.3.dist-info/RECORD
odinweb.django-0.4.3.dist-info/WHEEL
odinweb.django-0.4.3.dist-info/pbr.json
odinweb.django-0.4.3.dist-info/top_level.txt
