Metadata-Version: 2.1
Name: odinweb.django
Version: 0.4.3
Summary: Toolkit for building web API's using Odin and Django.
Home-page: https://github.com/python-odin/odinweb.django
Author: Tim Savage
Author-email: tim@savage.company
License: BSD
Keywords: web
Requires-Dist: odinweb (>=0.5)
Requires-Dist: django (>=1.8)
